aoiro/__init__.py
aoiro/__main__.py
aoiro/_ledger.py
aoiro/_multidimensional.py
aoiro/_sheets.py
aoiro/account.yml
aoiro/cli.py
aoiro/py.typed
aoiro/reader/__init__.py
aoiro/reader/_expenses.py
aoiro/reader/_io.py
aoiro/reader/_sales.py
aoiro-0.1.59.dist-info/LICENSE
aoiro-0.1.59.dist-info/METADATA
aoiro-0.1.59.dist-info/WHEEL
aoiro-0.1.59.dist-info/entry_points.txt
aoiro-0.1.59.dist-info/RECORD
