Metadata-Version: 2.3
Name: aoiro
Version: 0.1.59
Summary: CSV-based 青色申告 CLI app
License: AGPL-3.0-only
Author: 34j
Author-email: 34j.github@proton.me
Requires-Python: >=3.10,<4.0
Classifier: Development Status :: 2 - Pre-Alpha
Classifier: Intended Audience :: Developers
Classifier: License :: OSI Approved :: GNU Affero General Public License v3
Classifier: Natural Language :: English
Classifier: Operating System :: OS Independent
Classifier: Programming Language :: Python :: 3
Classifier: Programming Language :: Python :: 3.10
Classifier: Programming Language :: Python :: 3.11
Classifier: Programming Language :: Python :: 3.12
Classifier: Programming Language :: Python :: 3.13
Classifier: Topic :: Software Development :: Libraries
Requires-Dist: account-codes-jp (>=0.4.0,<0.5.0)
Requires-Dist: attrs (>=25.1.0,<26.0.0)
Requires-Dist: cyclopts (>=3.9.3,<4.0.0)
Requires-Dist: dateparser (>=1.2.1,<2.0.0)
Requires-Dist: networkx (>=3.4.2,<4.0.0)
Requires-Dist: openpyxl (>=3.1.5,<4.0.0)
Requires-Dist: pandas (>=2.2.3,<3.0.0)
Requires-Dist: requests-cache (>=1.2.1,<2.0.0)
Requires-Dist: rich (>=13.9.4,<14.0.0)
Project-URL: Bug Tracker, https://github.com/34j/aoiro/issues
Project-URL: Changelog, https://github.com/34j/aoiro/blob/main/CHANGELOG.md
Project-URL: Documentation, https://aoiro.readthedocs.io
Project-URL: Repository, https://github.com/34j/aoiro
